micasense/__init__.py
micasense/capture.py
micasense/dls.py
micasense/image.py
micasense/imageset.py
micasense/imageutils.py
micasense/metadata.py
micasense/panel.py
micasense/plotutils.py
micasense/utils.py
micasense_imageprocessing-0.1.2.dist-info/licenses/LICENSE
micasense_imageprocessing-0.1.2.dist-info/METADATA
micasense_imageprocessing-0.1.2.dist-info/WHEEL
micasense_imageprocessing-0.1.2.dist-info/top_level.txt
micasense_imageprocessing-0.1.2.dist-info/RECORD
