Metadata-Version: 2.4
Name: micasense_imageprocessing
Version: 0.1.2
Summary: Micasense Image Processing - Third Party Project
Author-email: Florian Maurer <maurer@fh-aachen.de>, "MicaSense, Inc." <github@micasense.com>
License-Expression: MIT
Project-URL: Homepage, https://github.com/brainergylab/micasense_imageprocessing
Classifier: Development Status :: 4 - Beta
Classifier: Intended Audience :: Developers
Classifier: Operating System :: OS Independent
Classifier: Topic :: Scientific/Engineering :: Image Processing
Classifier: Topic :: Software Development :: Libraries :: Python Modules
Classifier: Programming Language :: Python :: 3 :: Only
Classifier: Programming Language :: Python :: 3.9
Classifier: Programming Language :: Python :: 3.10
Classifier: Programming Language :: Python :: 3.11
Classifier: Programming Language :: Python :: 3.12
Classifier: Programming Language :: Python :: 3.13
Requires-Python: >=3.9
License-File: LICENSE
Requires-Dist: requests
Requires-Dist: numpy
Requires-Dist: opencv-python
Requires-Dist: gdal
Requires-Dist: pysolar
Requires-Dist: matplotlib
Requires-Dist: scikit-image
Requires-Dist: packaging
Requires-Dist: pyexiftool
Requires-Dist: pytz
Requires-Dist: pyzbar
Provides-Extra: test
Requires-Dist: pytest>=7.4.3; extra == "test"
Requires-Dist: pytest-cov; extra == "test"
Dynamic: license-file
